README.md
setup.py
quantdsl/__init__.py
quantdsl/__main__.py
quantdsl/calculate.py
quantdsl/defaults.py
quantdsl/exceptions.py
quantdsl/semantics.py
quantdsl/syntax.py
quantdsl.egg-info/PKG-INFO
quantdsl.egg-info/SOURCES.txt
quantdsl.egg-info/dependency_links.txt
quantdsl.egg-info/not-zip-safe
quantdsl.egg-info/pbr.json
quantdsl.egg-info/requires.txt
quantdsl.egg-info/top_level.txt
quantdsl/application/__init__.py
quantdsl/application/base.py
quantdsl/application/call_result_policy.py
quantdsl/application/persistence_policy.py
quantdsl/application/with_multithreading.py
quantdsl/application/with_multithreading_and_python_objects.py
quantdsl/application/with_pythonobjects.py
quantdsl/domain/__init__.py
quantdsl/domain/model/__init__.py
quantdsl/domain/model/call_dependencies.py
quantdsl/domain/model/call_dependents.py
quantdsl/domain/model/call_leafs.py
quantdsl/domain/model/call_link.py
quantdsl/domain/model/call_requirement.py
quantdsl/domain/model/call_result.py
quantdsl/domain/model/contract_specification.py
quantdsl/domain/model/contract_valuation.py
quantdsl/domain/model/market_calibration.py
quantdsl/domain/model/market_simulation.py
quantdsl/domain/model/perturbation_dependencies.py
quantdsl/domain/model/simulated_price.py
quantdsl/domain/model/simulated_price_requirements.py
quantdsl/domain/services/__init__.py
quantdsl/domain/services/call_links.py
quantdsl/domain/services/contract_valuations.py
quantdsl/domain/services/dependency_graphs.py
quantdsl/domain/services/parser.py
quantdsl/domain/services/price_processes.py
quantdsl/domain/services/schwartzsmith_old.py
quantdsl/domain/services/simulated_prices.py
quantdsl/domain/services/uuids.py
quantdsl/infrastructure/__init__.py
quantdsl/infrastructure/dependency_graph_subscriber.py
quantdsl/infrastructure/evaluation_subscriber.py
quantdsl/infrastructure/simulation_subscriber.py
quantdsl/infrastructure/event_sourced_repos/__init__.py
quantdsl/infrastructure/event_sourced_repos/call_dependencies_repo.py
quantdsl/infrastructure/event_sourced_repos/call_dependents_repo.py
quantdsl/infrastructure/event_sourced_repos/call_leafs_repo.py
quantdsl/infrastructure/event_sourced_repos/call_link_repo.py
